cml_parser/CML.g4
cml_parser/__init__.py
cml_parser/cml_model_builder.py
cml_parser/cml_objects.py
cml_parser/parser.py
cml_parser/service_cutter_objects.py
cml_parser/antlr/CMLLexer.py
cml_parser/antlr/CMLListener.py
cml_parser/antlr/CMLParser.py
cml_parser/antlr/CMLVisitor.py
cml_parser/antlr/__init__.py
cml_parser-0.5.0.dist-info/licenses/LICENSE
cml_parser-0.5.0.dist-info/METADATA
cml_parser-0.5.0.dist-info/WHEEL
cml_parser-0.5.0.dist-info/top_level.txt
cml_parser-0.5.0.dist-info/RECORD
