Metadata-Version: 2.4
Name: cml-parser
Version: 0.5.0
Summary: A Python parser for Context Mapper DSL (CML)
Author-email: Martin Herran <martin882003@gmail.com>
License: MIT License
Project-URL: Homepage, https://github.com/martin882003/cml-parser
Project-URL: Bug Tracker, https://github.com/martin882003/cml-parser/issues
Classifier: Programming Language :: Python :: 3
Classifier: Programming Language :: Python :: 3.10
Classifier: Programming Language :: Python :: 3.11
Classifier: Programming Language :: Python :: 3.12
Classifier: Programming Language :: Python :: 3.13
Classifier: Programming Language :: Python :: 3.14
Classifier: License :: OSI Approved :: MIT License
Classifier: Operating System :: OS Independent
Requires-Python: >=3.10
License-File: LICENSE
Requires-Dist: antlr4-python3-runtime>=4.13.0
Dynamic: license-file
